TileSeqMut/__init__.py
TileSeqMut/__main__.py
TileSeqMut/alignment.py
TileSeqMut/cluster.py
TileSeqMut/count_mut.py
TileSeqMut/help_functions.py
TileSeqMut/locate_mut.py
TileSeqMut/main.py
TileSeqMut/mergeruns.py
TileSeqMut/parse_clinvar.py
TileSeqMut/posterior.py
TileSeqMut/posterior_qc.py
TileSeqMut/process.py
TileSeqMut/random_ds.py
TileSeqMut/yogiroc_embeded.R
TileSeqMut/data/phix.fasta
TileSeqMut-0.6.945.data/scripts/makePRC
TileSeqMut-0.6.945.data/scripts/mergeRuns
TileSeqMut-0.6.945.data/scripts/posterior_QC
TileSeqMut-0.6.945.data/scripts/random_ds
TileSeqMut-0.6.945.data/scripts/tileseq_mut
TileSeqMut-0.6.945.dist-info/LICENSE
TileSeqMut-0.6.945.dist-info/METADATA
TileSeqMut-0.6.945.dist-info/WHEEL
TileSeqMut-0.6.945.dist-info/top_level.txt
TileSeqMut-0.6.945.dist-info/RECORD
