Metadata-Version: 2.1
Name: TileSeqMut
Version: 0.6.945
Summary: Analysis scriptsTileSeqMut for TileSeq sequencing data
Home-page: https://github.com/rothlab/tileseq_mutcount
Author: ROUJIA LI
Author-email: roujia.li@mail.utoronto.ca
License: UNKNOWN
Platform: UNKNOWN
Classifier: Development Status :: 3 - Alpha
Classifier: Intended Audience :: Developers
Classifier: Topic :: Software Development :: Build Tools
Classifier: License :: OSI Approved :: MIT License
Classifier: Programming Language :: Python :: 3.7
Classifier: Programming Language :: Python :: 3.8
Requires-Python: >=3.7
Requires-Dist: biopython
Requires-Dist: fpdf
Requires-Dist: matplotlib
Requires-Dist: numpy
Requires-Dist: pandas
Requires-Dist: progressbar
Requires-Dist: seaborn
